pyopenms_nightly-2.6.0.dev20201012.dist-info/WHEEL
pyopenms_nightly-2.6.0.dev20201012.dist-info/METADATA
pyopenms_nightly-2.6.0.dev20201012.dist-info/top_level.txt
pyopenms_nightly-2.6.0.dev20201012.dist-info/RECORD
pyopenms/Plotting.py
pyopenms/License.txt
pyopenms/sysinfo.py
pyopenms/pyopenms_1.cpython-35m-x86_64-linux-gnu.so
pyopenms/__init__.py
pyopenms/pyopenms_5.cpython-35m-x86_64-linux-gnu.so
pyopenms/Constants.py
pyopenms/pyopenms_7.cpython-35m-x86_64-linux-gnu.so
pyopenms/pyopenms_2.cpython-35m-x86_64-linux-gnu.so
pyopenms/pyopenms_3.cpython-35m-x86_64-linux-gnu.so
pyopenms/pyopenms_8.cpython-35m-x86_64-linux-gnu.so
pyopenms/all_modules.py
pyopenms/python_extras.py
pyopenms/version.py
pyopenms/docompile.py
pyopenms/pyopenms_6.cpython-35m-x86_64-linux-gnu.so
pyopenms/pyopenms_4.cpython-35m-x86_64-linux-gnu.so
pyopenms/qt_version_info.py
pyopenms/share/OpenMS/GUISTYLE/qtStyleSheet.qss
pyopenms/share/OpenMS/CHEMISTRY/Enzymes_RNA.xml
pyopenms/share/OpenMS/CHEMISTRY/NegativeAdducts.tsv
pyopenms/share/OpenMS/CHEMISTRY/HMDBMappingFile.tsv
pyopenms/share/OpenMS/CHEMISTRY/PSI-MOD.obo
pyopenms/share/OpenMS/CHEMISTRY/unimod.xml
pyopenms/share/OpenMS/CHEMISTRY/Elements.xml
pyopenms/share/OpenMS/CHEMISTRY/MetaboliteIsoModelNoised2.scale
pyopenms/share/OpenMS/CHEMISTRY/MetaboliteIsoModelNoised5.svm
pyopenms/share/OpenMS/CHEMISTRY/Custom_RNA_modifications.tsv
pyopenms/share/OpenMS/CHEMISTRY/MetaboliteIsoModelNoised2.svm
pyopenms/share/OpenMS/CHEMISTRY/Residues.xml
pyopenms/share/OpenMS/CHEMISTRY/XTandem_default_input.xml
pyopenms/share/OpenMS/CHEMISTRY/MetaboliteIsoModelNoised5.scale
pyopenms/share/OpenMS/CHEMISTRY/MetaboliteIsoModel.svm
pyopenms/share/OpenMS/CHEMISTRY/OMSSA_modification_mapping
pyopenms/share/OpenMS/CHEMISTRY/PositiveAdducts.tsv
pyopenms/share/OpenMS/CHEMISTRY/XLMOD.obo
pyopenms/share/OpenMS/CHEMISTRY/Modomics.tsv
pyopenms/share/OpenMS/CHEMISTRY/MetaboliteIsoModel.scale
pyopenms/share/OpenMS/CHEMISTRY/Enzymes.xml
pyopenms/share/OpenMS/CHEMISTRY/MissedCleavage.model
pyopenms/share/OpenMS/SCHEMAS/Param_1_0.xsd
pyopenms/share/OpenMS/SCHEMAS/ConsensusXML_1_6.xsd
pyopenms/share/OpenMS/SCHEMAS/ConsensusXML_1_0.xsd
