Metadata-Version: 2.1
Name: pyopenms-nightly
Version: 2.6.0.dev20201012
Summary: Python wrapper for C++ LCMS library OpenMS
Home-page: http://open-ms.de
Author: Uwe Schmitt
Author-email: uschmitt@mineway.de
Maintainer: Uwe Schmitt
Maintainer-email: uschmitt@mineway.de
License: http://opensource.org/licenses/BSD-3-Clause
Platform: any
Classifier: Development Status :: 4 - Beta
Classifier: Intended Audience :: Science/Research
Classifier: License :: OSI Approved :: BSD License
Classifier: Topic :: Scientific/Engineering :: Bio-Informatics
Classifier: Topic :: Scientific/Engineering :: Chemistry
Requires-Dist: numpy
